django_quill-0.1.0.dist-info/DESCRIPTION.rst
django_quill-0.1.0.dist-info/METADATA
django_quill-0.1.0.dist-info/metadata.json
django_quill-0.1.0.dist-info/RECORD
django_quill-0.1.0.dist-info/top_level.txt
django_quill-0.1.0.dist-info/WHEEL
quill/__init__.py
quill/admin.py
quill/apps.py
quill/fields.py
quill/helpers.py
quill/widgets.py
quill/migrations/__init__.py
quill/migrations/__init__.pyc
quill/migrations/__pycache__/__init__.cpython-35.pyc
quill/static/.DS_Store
quill/static/quill/.DS_Store
quill/static/quill/css/quill.css
quill/static/quill/css/vendor/quill-0.19.11.snow.css
quill/static/quill/js/.DS_Store
quill/static/quill/js/helpers.js
quill/static/quill/js/image.js
quill/static/quill/js/quill-django.js
quill/static/quill/js/build/.gitkeep
quill/static/quill/js/build/quill-django.js
quill/static/quill/js/build/quill-django.min.js
quill/static/quill/js/test/helpers.js
quill/static/quill/js/test/quill-django.js
quill/static/quill/js/vendor/SimpleAjaxUploader-1a6f62289d.min.js
quill/templates/quill/editor.html
quill/templates/quill/widget.html
quill/templates/quill/toolbars/basic.html
quill/templates/quill/toolbars/full.html
quill/templatetags/__init__.py
quill/templatetags/__init__.pyc
quill/templatetags/quill_tags.py
quill/templatetags/quill_tags.pyc
quill/templatetags/__pycache__/__init__.cpython-34.pyc
quill/templatetags/__pycache__/__init__.cpython-35.pyc
quill/templatetags/__pycache__/quill_tags.cpython-34.pyc
quill/templatetags/__pycache__/quill_tags.cpython-35.pyc
