Metadata-Version: 1.1
Name: django-quill
Version: 0.1.0
Summary: Easily use Quill.js in your django admin.
Home-page: UNKNOWN
Author: Ryan Senkbeil
Author-email: ryan.senkbeil@gsdesign.com
License: UNKNOWN
Platform: any
Classifier: Development Status :: 4 - Beta
Classifier: Environment :: Web Environment
Classifier: Framework :: Django
Classifier: Intended Audience :: Developers
Classifier: License :: OSI Approved :: BSD License
Classifier: Operating System :: OS Independent
Classifier: Programming Language :: Python
Classifier: Programming Language :: Python :: 3
Classifier: Topic :: Internet :: WWW/HTTP
